{
  "projects": [
    {
      "id": "1",
      "name": "project 1"
    },
    {
      "id": "2",
      "name": "project 2"
    },
    {
      "id": "3",
      "name": "project 3"
    },
    {
      "id": "4",
      "name": "project 4"
    },
    {
      "id": "5",
      "name": "project 5"
    }
  ],
  "tasks": [
    {
      "id": "a0244ddb-3b2b-42e2-a6b5-835cc20d968d",
      "project_id": "2",
      "name": "aaaa",
      "start_date": "2024-02-23",
      "end_date": "2024-02-25",
      "is_completed": false
    },
    {
      "id": "e833fa7c-4264-4c09-8a35-10bfbfea8429",
      "project_id": "3",
      "name": "bbbb",
      "start_date": "2024-02-23",
      "end_date": "2024-02-24",
      "is_completed": false
    },
    {
      "id": "3c8df4d9-342a-49d7-a048-ae00ece18eca",
      "project_id": "2",
      "name": "ggggg",
      "start_date": "2024-02-28",
      "end_date": "2024-03-05",
      "is_completed": false
    }
  ]
}